app_common/__init__.py
app_common/app_common.py
app_wrapper/__init__.py
app_wrapper/app_wrapper.py
AppWrapper-0.2.1.dist-info/METADATA
AppWrapper-0.2.1.dist-info/WHEEL
AppWrapper-0.2.1.dist-info/top_level.txt
AppWrapper-0.2.1.dist-info/RECORD
