Metadata-Version: 2.1
Name: AppWrapper
Version: 0.2.1
Summary: Library for Superb-AI Apps
Requires-Dist: requests (>=2.0.0)
Requires-Dist: boto3 (>=1.13.4)
